dynafield/__init__.py
dynafield/base_model.py
dynafield/from_func.py
dynafield/record_schema.py
dynafield/utils.py
dynafield/fields/__init__.py
dynafield/fields/base_field.py
dynafield/fields/bool_field.py
dynafield/fields/date_field.py
dynafield/fields/email_field.py
dynafield/fields/enum_field.py
dynafield/fields/float_field.py
dynafield/fields/int_field.py
dynafield/fields/json_field.py
dynafield/fields/list_field.py
dynafield/fields/object_field.py
dynafield/fields/str_field.py
dynafield/fields/uuid_field.py
dynafield-0.0.8.dist-info/licenses/LICENSE
dynafield-0.0.8.dist-info/METADATA
dynafield-0.0.8.dist-info/WHEEL
dynafield-0.0.8.dist-info/top_level.txt
dynafield-0.0.8.dist-info/RECORD
