Metadata-Version: 2.4
Name: dynafield
Version: 0.0.8
Summary: Dynamic fields build up schema
Author-email: Badr Elfarri <badr@revvue.ai>, Magnus Mariero <magnus@revvue.ai>
Maintainer-email: Badr Elfarri <badr@revvue.ai>, Magnus Mariero <magnus@revvue.ai>
License: Apache-2.0
Project-URL: Homepage, https://github.com/revvue-ai/dynafield
Project-URL: Documentation, https://github.com/revvue-ai/dynafield#readme
Project-URL: Repository, https://github.com/revvue-ai/dynafield
Project-URL: Bug Tracker, https://github.com/revvue-ai/dynafield/issues
Project-URL: Changelog, https://github.com/revvue-ai/dynafield/blob/main/CHANGELOG.md
Keywords: dynamic fields,toolkit,async
Classifier: Development Status :: 3 - Alpha
Classifier: Intended Audience :: Developers
Classifier: License :: OSI Approved :: Apache Software License
Classifier: Programming Language :: Python :: 3
Requires-Python: <3.13,>=3.12
License-File: LICENSE
Requires-Dist: uvicorn
Requires-Dist: pydantic[email]
Requires-Dist: httpx
Requires-Dist: fastapi
Requires-Dist: uuid-utils
Requires-Dist: strawberry-graphql[debug-server,fastapi]
Dynamic: license-file
